soda_python_sdk/__init__.py
soda_python_sdk/crypto.py
soda_python_sdk/test.py
gcevm_sdk-0.0.5.dist-info/METADATA
gcevm_sdk-0.0.5.dist-info/WHEEL
gcevm_sdk-0.0.5.dist-info/top_level.txt
gcevm_sdk-0.0.5.dist-info/RECORD
